bd_extrusions/__init__.py
bd_extrusions/vslot.py
bd_extrusions/utils/array.py
bd_extrusions/utils/locations.py
bd_extrusions-0.0.1.dist-info/LICENSE
bd_extrusions-0.0.1.dist-info/METADATA
bd_extrusions-0.0.1.dist-info/WHEEL
bd_extrusions-0.0.1.dist-info/top_level.txt
bd_extrusions-0.0.1.dist-info/RECORD
